[{"path":"src/main/java/Ruan.java","fileType":"java","lines":[{"lineNumber":1,"author":{"gitId":"jianjunruan"},"content":"import java.util.*;","lastModifiedDate":"2024-08-27","isFullCredit":false},{"lineNumber":2,"author":{"gitId":"jianjunruan"},"content":"public class Ruan {","lastModifiedDate":"2024-08-27","isFullCredit":false},{"lineNumber":3,"author":{"gitId":"jianjunruan"},"content":"   ","lastModifiedDate":"2024-09-03","isFullCredit":false},{"lineNumber":4,"author":{"gitId":"jianjunruan"},"content":"    public static void main(String[] args) {","lastModifiedDate":"2024-08-27","isFullCredit":false},{"lineNumber":5,"author":{"gitId":"jianjunruan"},"content":"        // String logo \u003d \" ____        _        \\n\"","lastModifiedDate":"2024-08-27","isFullCredit":false},{"lineNumber":6,"author":{"gitId":"jianjunruan"},"content":"        //         + \"|  _ \\\\ _   _| | _____ \\n\"","lastModifiedDate":"2024-08-27","isFullCredit":false},{"lineNumber":7,"author":{"gitId":"jianjunruan"},"content":"        //         + \"| | | | | | | |/ / _ \\\\\\n\"","lastModifiedDate":"2024-08-27","isFullCredit":false},{"lineNumber":8,"author":{"gitId":"jianjunruan"},"content":"        //         + \"| |_| | |_| |   \u003c  __/\\n\"","lastModifiedDate":"2024-08-27","isFullCredit":false},{"lineNumber":9,"author":{"gitId":"jianjunruan"},"content":"        //         + \"|____/ \\\\__,_|_|\\\\_\\\\___|\\n\";","lastModifiedDate":"2024-08-27","isFullCredit":false},{"lineNumber":10,"author":{"gitId":"jianjunruan"},"content":"        // System.out.println(\"Hello from\\n\" + logo);","lastModifiedDate":"2024-08-27","isFullCredit":false},{"lineNumber":11,"author":{"gitId":"jianjunruan"},"content":"","lastModifiedDate":"2024-08-27","isFullCredit":false},{"lineNumber":12,"author":{"gitId":"jianjunruan"},"content":"        String line \u003d \"\";","lastModifiedDate":"2024-08-27","isFullCredit":false},{"lineNumber":13,"author":{"gitId":"jianjunruan"},"content":"        TaskList taskList \u003d new TaskList();//declare tasklist, call TaskList class","lastModifiedDate":"2024-10-20","isFullCredit":false},{"lineNumber":14,"author":{"gitId":"jianjunruan"},"content":"        ","lastModifiedDate":"2024-10-20","isFullCredit":false},{"lineNumber":15,"author":{"gitId":"jianjunruan"},"content":"        try(Scanner userInput \u003d new Scanner(System.in)){//declare input scanner","lastModifiedDate":"2024-10-20","isFullCredit":false},{"lineNumber":16,"author":{"gitId":"jianjunruan"},"content":"","lastModifiedDate":"2024-08-27","isFullCredit":false},{"lineNumber":17,"author":{"gitId":"jianjunruan"},"content":"            System.out.println(\"  -----------------------------------\");","lastModifiedDate":"2024-08-27","isFullCredit":false},{"lineNumber":18,"author":{"gitId":"jianjunruan"},"content":"            System.out.println(\"  Hello, I\u0027m Ruan\\n  What can I do for you?\");","lastModifiedDate":"2024-08-27","isFullCredit":false},{"lineNumber":19,"author":{"gitId":"jianjunruan"},"content":"            System.out.println(\"  -----------------------------------\");","lastModifiedDate":"2024-08-27","isFullCredit":false},{"lineNumber":20,"author":{"gitId":"jianjunruan"},"content":"","lastModifiedDate":"2024-08-27","isFullCredit":false},{"lineNumber":21,"author":{"gitId":"jianjunruan"},"content":"            while(!line.trim().toLowerCase().equals(\"bye\")){","lastModifiedDate":"2024-08-27","isFullCredit":false},{"lineNumber":22,"author":{"gitId":"jianjunruan"},"content":"                line \u003d userInput.nextLine();","lastModifiedDate":"2024-08-27","isFullCredit":false},{"lineNumber":23,"author":{"gitId":"jianjunruan"},"content":"","lastModifiedDate":"2024-09-03","isFullCredit":false},{"lineNumber":24,"author":{"gitId":"jianjunruan"},"content":"                //check for \"bye\"","lastModifiedDate":"2024-09-03","isFullCredit":false},{"lineNumber":25,"author":{"gitId":"jianjunruan"},"content":"                if(line.trim().toLowerCase().equals(\"bye\")){","lastModifiedDate":"2024-08-27","isFullCredit":false},{"lineNumber":26,"author":{"gitId":"jianjunruan"},"content":"                    System.out.println(\"Bye. Hope to see you again soon!\");","lastModifiedDate":"2024-10-20","isFullCredit":false},{"lineNumber":27,"author":{"gitId":"jianjunruan"},"content":"                    break;","lastModifiedDate":"2024-10-20","isFullCredit":false},{"lineNumber":28,"author":{"gitId":"jianjunruan"},"content":"                }","lastModifiedDate":"2024-10-20","isFullCredit":false},{"lineNumber":29,"author":{"gitId":"jianjunruan"},"content":"                ","lastModifiedDate":"2024-10-20","isFullCredit":false},{"lineNumber":30,"author":{"gitId":"jianjunruan"},"content":"                //handle specific commands","lastModifiedDate":"2024-10-20","isFullCredit":false},{"lineNumber":31,"author":{"gitId":"jianjunruan"},"content":"                if (line.toLowerCase().startsWith(\"mark\")) {","lastModifiedDate":"2024-10-20","isFullCredit":false},{"lineNumber":32,"author":{"gitId":"jianjunruan"},"content":"                    //action for mark item","lastModifiedDate":"2024-10-20","isFullCredit":false},{"lineNumber":33,"author":{"gitId":"jianjunruan"},"content":"","lastModifiedDate":"2024-10-20","isFullCredit":false},{"lineNumber":34,"author":{"gitId":"jianjunruan"},"content":"                    //explode line command and get task number from last item","lastModifiedDate":"2024-10-20","isFullCredit":false},{"lineNumber":35,"author":{"gitId":"jianjunruan"},"content":"                    int taskNo \u003d Integer.parseInt(line.split(\" \")[1]) - 1;","lastModifiedDate":"2024-10-20","isFullCredit":false},{"lineNumber":36,"author":{"gitId":"jianjunruan"},"content":"                    taskList.markTask(taskNo);","lastModifiedDate":"2024-10-20","isFullCredit":false},{"lineNumber":37,"author":{"gitId":"jianjunruan"},"content":"                } else if (line.toLowerCase().startsWith(\"unmark\")) {","lastModifiedDate":"2024-10-20","isFullCredit":false},{"lineNumber":38,"author":{"gitId":"jianjunruan"},"content":"                    //action for unmark item","lastModifiedDate":"2024-10-20","isFullCredit":false},{"lineNumber":39,"author":{"gitId":"jianjunruan"},"content":"","lastModifiedDate":"2024-10-20","isFullCredit":false},{"lineNumber":40,"author":{"gitId":"jianjunruan"},"content":"                    //explode line command and get task number from last item","lastModifiedDate":"2024-10-20","isFullCredit":false},{"lineNumber":41,"author":{"gitId":"jianjunruan"},"content":"                    int taskNo \u003d Integer.parseInt(line.split(\" \")[1]) - 1;","lastModifiedDate":"2024-10-20","isFullCredit":false},{"lineNumber":42,"author":{"gitId":"jianjunruan"},"content":"                    taskList.unmarkTask(taskNo);","lastModifiedDate":"2024-10-20","isFullCredit":false},{"lineNumber":43,"author":{"gitId":"jianjunruan"},"content":"                }else if (line.trim().toLowerCase().equals(\"list\")) {","lastModifiedDate":"2024-10-20","isFullCredit":false},{"lineNumber":44,"author":{"gitId":"jianjunruan"},"content":"                    //handle the \"list\" command to display tasks","lastModifiedDate":"2024-10-20","isFullCredit":false},{"lineNumber":45,"author":{"gitId":"jianjunruan"},"content":"                    taskList.printList();","lastModifiedDate":"2024-10-20","isFullCredit":false},{"lineNumber":46,"author":{"gitId":"jianjunruan"},"content":"                }else {","lastModifiedDate":"2024-09-03","isFullCredit":false},{"lineNumber":47,"author":{"gitId":"jianjunruan"},"content":"                    //add task to the task list","lastModifiedDate":"2024-10-20","isFullCredit":false},{"lineNumber":48,"author":{"gitId":"jianjunruan"},"content":"                    taskList.addTask(line);","lastModifiedDate":"2024-10-20","isFullCredit":false},{"lineNumber":49,"author":{"gitId":"jianjunruan"},"content":"                }","lastModifiedDate":"2024-09-03","isFullCredit":false},{"lineNumber":50,"author":{"gitId":"jianjunruan"},"content":"","lastModifiedDate":"2024-08-27","isFullCredit":false},{"lineNumber":51,"author":{"gitId":"jianjunruan"},"content":"            }","lastModifiedDate":"2024-08-27","isFullCredit":false},{"lineNumber":52,"author":{"gitId":"jianjunruan"},"content":"        }","lastModifiedDate":"2024-08-27","isFullCredit":false},{"lineNumber":53,"author":{"gitId":"jianjunruan"},"content":"","lastModifiedDate":"2024-09-03","isFullCredit":false},{"lineNumber":54,"author":{"gitId":"jianjunruan"},"content":"    }","lastModifiedDate":"2024-08-27","isFullCredit":false},{"lineNumber":55,"author":{"gitId":"jianjunruan"},"content":"}","lastModifiedDate":"2024-08-27","isFullCredit":false}],"authorContributionMap":{"jianjunruan":55}},{"path":"src/main/java/Task.java","fileType":"java","lines":[{"lineNumber":1,"author":{"gitId":"jianjunruan"},"content":"public class Task {","lastModifiedDate":"2024-10-20","isFullCredit":false},{"lineNumber":2,"author":{"gitId":"jianjunruan"},"content":"    protected String description;","lastModifiedDate":"2024-10-20","isFullCredit":false},{"lineNumber":3,"author":{"gitId":"jianjunruan"},"content":"    protected boolean isDone;","lastModifiedDate":"2024-10-20","isFullCredit":false},{"lineNumber":4,"author":{"gitId":"jianjunruan"},"content":"","lastModifiedDate":"2024-10-20","isFullCredit":false},{"lineNumber":5,"author":{"gitId":"jianjunruan"},"content":"    //initial Task","lastModifiedDate":"2024-10-20","isFullCredit":false},{"lineNumber":6,"author":{"gitId":"jianjunruan"},"content":"    public Task(String description) {","lastModifiedDate":"2024-10-20","isFullCredit":false},{"lineNumber":7,"author":{"gitId":"jianjunruan"},"content":"        this.description \u003d description;","lastModifiedDate":"2024-10-20","isFullCredit":false},{"lineNumber":8,"author":{"gitId":"jianjunruan"},"content":"        this.isDone \u003d false;//default all item set to not done","lastModifiedDate":"2024-10-20","isFullCredit":false},{"lineNumber":9,"author":{"gitId":"jianjunruan"},"content":"    }","lastModifiedDate":"2024-10-20","isFullCredit":false},{"lineNumber":10,"author":{"gitId":"jianjunruan"},"content":"","lastModifiedDate":"2024-10-20","isFullCredit":false},{"lineNumber":11,"author":{"gitId":"jianjunruan"},"content":"    // get item status","lastModifiedDate":"2024-10-20","isFullCredit":false},{"lineNumber":12,"author":{"gitId":"jianjunruan"},"content":"    public String getStatusIcon() {","lastModifiedDate":"2024-10-20","isFullCredit":false},{"lineNumber":13,"author":{"gitId":"jianjunruan"},"content":"        return (isDone ? \"X\" : \" \");","lastModifiedDate":"2024-10-20","isFullCredit":false},{"lineNumber":14,"author":{"gitId":"jianjunruan"},"content":"    }","lastModifiedDate":"2024-10-20","isFullCredit":false},{"lineNumber":15,"author":{"gitId":"jianjunruan"},"content":"","lastModifiedDate":"2024-10-20","isFullCredit":false},{"lineNumber":16,"author":{"gitId":"jianjunruan"},"content":"    //mark item as done","lastModifiedDate":"2024-10-20","isFullCredit":false},{"lineNumber":17,"author":{"gitId":"jianjunruan"},"content":"    public void markDone() {","lastModifiedDate":"2024-10-20","isFullCredit":false},{"lineNumber":18,"author":{"gitId":"jianjunruan"},"content":"        isDone \u003d true; ","lastModifiedDate":"2024-10-20","isFullCredit":false},{"lineNumber":19,"author":{"gitId":"jianjunruan"},"content":"    }","lastModifiedDate":"2024-10-20","isFullCredit":false},{"lineNumber":20,"author":{"gitId":"jianjunruan"},"content":"","lastModifiedDate":"2024-10-20","isFullCredit":false},{"lineNumber":21,"author":{"gitId":"jianjunruan"},"content":"    //unmark item, set not done","lastModifiedDate":"2024-10-20","isFullCredit":false},{"lineNumber":22,"author":{"gitId":"jianjunruan"},"content":"    public void unmarkDone() {","lastModifiedDate":"2024-10-20","isFullCredit":false},{"lineNumber":23,"author":{"gitId":"jianjunruan"},"content":"        isDone \u003d false; ","lastModifiedDate":"2024-10-20","isFullCredit":false},{"lineNumber":24,"author":{"gitId":"jianjunruan"},"content":"    }","lastModifiedDate":"2024-10-20","isFullCredit":false},{"lineNumber":25,"author":{"gitId":"jianjunruan"},"content":"","lastModifiedDate":"2024-10-20","isFullCredit":false},{"lineNumber":26,"author":{"gitId":"jianjunruan"},"content":"    @Override","lastModifiedDate":"2024-10-20","isFullCredit":false},{"lineNumber":27,"author":{"gitId":"jianjunruan"},"content":"    //convert into string msg","lastModifiedDate":"2024-10-20","isFullCredit":false},{"lineNumber":28,"author":{"gitId":"jianjunruan"},"content":"    public String toString() {","lastModifiedDate":"2024-10-20","isFullCredit":false},{"lineNumber":29,"author":{"gitId":"jianjunruan"},"content":"        return \"[\" + getStatusIcon() + \"] \" + description; ","lastModifiedDate":"2024-10-20","isFullCredit":false},{"lineNumber":30,"author":{"gitId":"jianjunruan"},"content":"    }","lastModifiedDate":"2024-10-20","isFullCredit":false},{"lineNumber":31,"author":{"gitId":"jianjunruan"},"content":"}","lastModifiedDate":"2024-10-20","isFullCredit":false}],"authorContributionMap":{"jianjunruan":31}},{"path":"src/main/java/TaskList.java","fileType":"java","lines":[{"lineNumber":1,"author":{"gitId":"jianjunruan"},"content":"public class TaskList {","lastModifiedDate":"2024-10-20","isFullCredit":false},{"lineNumber":2,"author":{"gitId":"jianjunruan"},"content":"    private Task[] taskList;//declare task array","lastModifiedDate":"2024-10-20","isFullCredit":false},{"lineNumber":3,"author":{"gitId":"jianjunruan"},"content":"    private int listCount;//declare count variable","lastModifiedDate":"2024-10-20","isFullCredit":false},{"lineNumber":4,"author":{"gitId":"jianjunruan"},"content":"","lastModifiedDate":"2024-10-20","isFullCredit":false},{"lineNumber":5,"author":{"gitId":"jianjunruan"},"content":"    //initial TaskList","lastModifiedDate":"2024-10-20","isFullCredit":false},{"lineNumber":6,"author":{"gitId":"jianjunruan"},"content":"    public TaskList() {","lastModifiedDate":"2024-10-20","isFullCredit":false},{"lineNumber":7,"author":{"gitId":"jianjunruan"},"content":"        this.taskList \u003d new Task[100];  //assume a maximum of 100 tasks for now","lastModifiedDate":"2024-10-20","isFullCredit":false},{"lineNumber":8,"author":{"gitId":"jianjunruan"},"content":"        this.listCount \u003d 0;","lastModifiedDate":"2024-10-20","isFullCredit":false},{"lineNumber":9,"author":{"gitId":"jianjunruan"},"content":"    }","lastModifiedDate":"2024-10-20","isFullCredit":false},{"lineNumber":10,"author":{"gitId":"jianjunruan"},"content":"","lastModifiedDate":"2024-10-20","isFullCredit":false},{"lineNumber":11,"author":{"gitId":"jianjunruan"},"content":"    //add a new task to the task list","lastModifiedDate":"2024-10-20","isFullCredit":false},{"lineNumber":12,"author":{"gitId":"jianjunruan"},"content":"    public void addTask(String description) {","lastModifiedDate":"2024-10-20","isFullCredit":false},{"lineNumber":13,"author":{"gitId":"jianjunruan"},"content":"        taskList[listCount] \u003d new Task(description);","lastModifiedDate":"2024-10-20","isFullCredit":false},{"lineNumber":14,"author":{"gitId":"jianjunruan"},"content":"        String[] lineOut \u003d new String[100];","lastModifiedDate":"2024-10-20","isFullCredit":false},{"lineNumber":15,"author":{"gitId":"jianjunruan"},"content":"        lineOut[0] \u003d \"added: \" + description;","lastModifiedDate":"2024-10-20","isFullCredit":false},{"lineNumber":16,"author":{"gitId":"jianjunruan"},"content":"        print(lineOut);","lastModifiedDate":"2024-10-20","isFullCredit":false},{"lineNumber":17,"author":{"gitId":"jianjunruan"},"content":"        listCount++;","lastModifiedDate":"2024-10-20","isFullCredit":false},{"lineNumber":18,"author":{"gitId":"jianjunruan"},"content":"    }","lastModifiedDate":"2024-10-20","isFullCredit":false},{"lineNumber":19,"author":{"gitId":"jianjunruan"},"content":"","lastModifiedDate":"2024-10-20","isFullCredit":false},{"lineNumber":20,"author":{"gitId":"jianjunruan"},"content":"    //mark a task as done based on its index","lastModifiedDate":"2024-10-20","isFullCredit":false},{"lineNumber":21,"author":{"gitId":"jianjunruan"},"content":"    public void markTask(int index) {","lastModifiedDate":"2024-10-20","isFullCredit":false},{"lineNumber":22,"author":{"gitId":"jianjunruan"},"content":"        if (index \u003e\u003d 0 \u0026\u0026 index \u003c listCount) {","lastModifiedDate":"2024-10-20","isFullCredit":false},{"lineNumber":23,"author":{"gitId":"jianjunruan"},"content":"            taskList[index].markDone();","lastModifiedDate":"2024-10-20","isFullCredit":false},{"lineNumber":24,"author":{"gitId":"jianjunruan"},"content":"            String[] lineOut \u003d new String[100];","lastModifiedDate":"2024-10-20","isFullCredit":false},{"lineNumber":25,"author":{"gitId":"jianjunruan"},"content":"            lineOut[0] \u003d \"Nice! I\u0027ve marked this task as done:\";","lastModifiedDate":"2024-10-20","isFullCredit":false},{"lineNumber":26,"author":{"gitId":"jianjunruan"},"content":"            lineOut[1] \u003d \"  \" + taskList[index];","lastModifiedDate":"2024-10-20","isFullCredit":false},{"lineNumber":27,"author":{"gitId":"jianjunruan"},"content":"            print(lineOut);","lastModifiedDate":"2024-10-20","isFullCredit":false},{"lineNumber":28,"author":{"gitId":"jianjunruan"},"content":"        } ","lastModifiedDate":"2024-10-20","isFullCredit":false},{"lineNumber":29,"author":{"gitId":"jianjunruan"},"content":"    }","lastModifiedDate":"2024-10-20","isFullCredit":false},{"lineNumber":30,"author":{"gitId":"jianjunruan"},"content":"","lastModifiedDate":"2024-10-20","isFullCredit":false},{"lineNumber":31,"author":{"gitId":"jianjunruan"},"content":"    //mark a task as not done based on its index","lastModifiedDate":"2024-10-20","isFullCredit":false},{"lineNumber":32,"author":{"gitId":"jianjunruan"},"content":"    public void unmarkTask(int index) {","lastModifiedDate":"2024-10-20","isFullCredit":false},{"lineNumber":33,"author":{"gitId":"jianjunruan"},"content":"        if (index \u003e\u003d 0 \u0026\u0026 index \u003c listCount) {","lastModifiedDate":"2024-10-20","isFullCredit":false},{"lineNumber":34,"author":{"gitId":"jianjunruan"},"content":"            taskList[index].unmarkDone();","lastModifiedDate":"2024-10-20","isFullCredit":false},{"lineNumber":35,"author":{"gitId":"jianjunruan"},"content":"            String[] lineOut \u003d new String[100];","lastModifiedDate":"2024-10-20","isFullCredit":false},{"lineNumber":36,"author":{"gitId":"jianjunruan"},"content":"            lineOut[0] \u003d \"OK, I\u0027ve marked this task as not done yet:\";","lastModifiedDate":"2024-10-20","isFullCredit":false},{"lineNumber":37,"author":{"gitId":"jianjunruan"},"content":"            lineOut[1] \u003d \"  \" + taskList[index];","lastModifiedDate":"2024-10-20","isFullCredit":false},{"lineNumber":38,"author":{"gitId":"jianjunruan"},"content":"            print(lineOut);","lastModifiedDate":"2024-10-20","isFullCredit":false},{"lineNumber":39,"author":{"gitId":"jianjunruan"},"content":"        }","lastModifiedDate":"2024-10-20","isFullCredit":false},{"lineNumber":40,"author":{"gitId":"jianjunruan"},"content":"    }","lastModifiedDate":"2024-10-20","isFullCredit":false},{"lineNumber":41,"author":{"gitId":"jianjunruan"},"content":"","lastModifiedDate":"2024-10-20","isFullCredit":false},{"lineNumber":42,"author":{"gitId":"jianjunruan"},"content":"    //print the list of tasks","lastModifiedDate":"2024-10-20","isFullCredit":false},{"lineNumber":43,"author":{"gitId":"jianjunruan"},"content":"    public void printList() {","lastModifiedDate":"2024-10-20","isFullCredit":false},{"lineNumber":44,"author":{"gitId":"jianjunruan"},"content":"","lastModifiedDate":"2024-10-20","isFullCredit":false},{"lineNumber":45,"author":{"gitId":"jianjunruan"},"content":"        String[] lineOut \u003d new String[100];","lastModifiedDate":"2024-10-20","isFullCredit":false},{"lineNumber":46,"author":{"gitId":"jianjunruan"},"content":"        //print list msg","lastModifiedDate":"2024-10-20","isFullCredit":false},{"lineNumber":47,"author":{"gitId":"jianjunruan"},"content":"        lineOut[0] \u003d \"Here are the tasks in your list:\";","lastModifiedDate":"2024-10-20","isFullCredit":false},{"lineNumber":48,"author":{"gitId":"jianjunruan"},"content":"","lastModifiedDate":"2024-10-20","isFullCredit":false},{"lineNumber":49,"author":{"gitId":"jianjunruan"},"content":"        int taskNo \u003d 1;","lastModifiedDate":"2024-10-20","isFullCredit":false},{"lineNumber":50,"author":{"gitId":"jianjunruan"},"content":" ","lastModifiedDate":"2024-10-20","isFullCredit":false},{"lineNumber":51,"author":{"gitId":"jianjunruan"},"content":"        for (Task task : taskList) {","lastModifiedDate":"2024-10-20","isFullCredit":false},{"lineNumber":52,"author":{"gitId":"jianjunruan"},"content":"            if(task \u003d\u003d null){","lastModifiedDate":"2024-10-20","isFullCredit":false},{"lineNumber":53,"author":{"gitId":"jianjunruan"},"content":"                break;//exit this loop and continue","lastModifiedDate":"2024-10-20","isFullCredit":false},{"lineNumber":54,"author":{"gitId":"jianjunruan"},"content":"            }","lastModifiedDate":"2024-10-20","isFullCredit":false},{"lineNumber":55,"author":{"gitId":"jianjunruan"},"content":"","lastModifiedDate":"2024-10-20","isFullCredit":false},{"lineNumber":56,"author":{"gitId":"jianjunruan"},"content":"            //print only when there is value","lastModifiedDate":"2024-10-20","isFullCredit":false},{"lineNumber":57,"author":{"gitId":"jianjunruan"},"content":"            lineOut[taskNo] \u003d taskNo+\". \"+task;","lastModifiedDate":"2024-10-20","isFullCredit":false},{"lineNumber":58,"author":{"gitId":"jianjunruan"},"content":"            taskNo++;// increase task number","lastModifiedDate":"2024-10-20","isFullCredit":false},{"lineNumber":59,"author":{"gitId":"jianjunruan"},"content":"        }","lastModifiedDate":"2024-10-20","isFullCredit":false},{"lineNumber":60,"author":{"gitId":"jianjunruan"},"content":"        print(lineOut);","lastModifiedDate":"2024-10-20","isFullCredit":false},{"lineNumber":61,"author":{"gitId":"jianjunruan"},"content":"    }","lastModifiedDate":"2024-10-20","isFullCredit":false},{"lineNumber":62,"author":{"gitId":"jianjunruan"},"content":"","lastModifiedDate":"2024-10-20","isFullCredit":false},{"lineNumber":63,"author":{"gitId":"jianjunruan"},"content":"","lastModifiedDate":"2024-10-20","isFullCredit":false},{"lineNumber":64,"author":{"gitId":"jianjunruan"},"content":"    public void print(String[] lineOut){","lastModifiedDate":"2024-10-20","isFullCredit":false},{"lineNumber":65,"author":{"gitId":"jianjunruan"},"content":"        System.out.println(\"  -----------------------------------\");","lastModifiedDate":"2024-10-20","isFullCredit":false},{"lineNumber":66,"author":{"gitId":"jianjunruan"},"content":"        for(String line: lineOut){","lastModifiedDate":"2024-10-20","isFullCredit":false},{"lineNumber":67,"author":{"gitId":"jianjunruan"},"content":"            if(line \u003d\u003d null){","lastModifiedDate":"2024-10-20","isFullCredit":false},{"lineNumber":68,"author":{"gitId":"jianjunruan"},"content":"                break;//exit this loop and continue","lastModifiedDate":"2024-10-20","isFullCredit":false},{"lineNumber":69,"author":{"gitId":"jianjunruan"},"content":"            }","lastModifiedDate":"2024-10-20","isFullCredit":false},{"lineNumber":70,"author":{"gitId":"jianjunruan"},"content":"            System.out.println(\"  \"+line);","lastModifiedDate":"2024-10-20","isFullCredit":false},{"lineNumber":71,"author":{"gitId":"jianjunruan"},"content":"        }","lastModifiedDate":"2024-10-20","isFullCredit":false},{"lineNumber":72,"author":{"gitId":"jianjunruan"},"content":"        System.out.println(\"  -----------------------------------\");","lastModifiedDate":"2024-10-20","isFullCredit":false},{"lineNumber":73,"author":{"gitId":"jianjunruan"},"content":"    }","lastModifiedDate":"2024-10-20","isFullCredit":false},{"lineNumber":74,"author":{"gitId":"jianjunruan"},"content":"","lastModifiedDate":"2024-10-20","isFullCredit":false},{"lineNumber":75,"author":{"gitId":"jianjunruan"},"content":" ","lastModifiedDate":"2024-10-20","isFullCredit":false},{"lineNumber":76,"author":{"gitId":"jianjunruan"},"content":"}","lastModifiedDate":"2024-10-20","isFullCredit":false}],"authorContributionMap":{"jianjunruan":76}}]
